django_health_monitor-0.2.8.dist-info/DESCRIPTION.rst
django_health_monitor-0.2.8.dist-info/METADATA
django_health_monitor-0.2.8.dist-info/RECORD
django_health_monitor-0.2.8.dist-info/WHEEL
django_health_monitor-0.2.8.dist-info/metadata.json
django_health_monitor-0.2.8.dist-info/top_level.txt
health_monitor/__init__.py
health_monitor/models.py
health_monitor/utils.py
health_monitor/views.py
health_monitor/static/css/health_monitor.css
health_monitor/static/js/health_monitor.js
health_monitor/templates/health_monitor/base.html
tests/__init__.py
tests/models.py
tests/test_settings.py
tests/urls.py
tests/utils.py
tests/views.py
tests/migrations/0001_initial.py
tests/migrations/0002_bodyhealth_history.py
tests/migrations/0003_smokehealthtest.py
tests/migrations/__init__.py
tests/tests/__init__.py
tests/tests/test_integration_health.py
tests/tests/test_integration_health_alarm.py
tests/tests/test_unit_health.py
tests/tests/test_unit_health_test.py
