Metadata-Version: 2.0
Name: django-health-monitor
Version: 0.2.8
Summary: A Django  app to help track system health and give real-time feedback.
Home-page: https://github.com/gracenote/django-health-monitor
Author: Sean Chon
Author-email: s@seanchon.com
License: Apache License 2.0
Keywords: django-health-monitor
Platform: UNKNOWN
Classifier: Development Status :: 3 - Alpha
Classifier: Framework :: Django
Classifier: Framework :: Django :: 1.8
Classifier: Framework :: Django :: 1.9
Classifier: Framework :: Django :: 1.10
Classifier: Framework :: Django :: 1.11
Classifier: Intended Audience :: Developers
Classifier: License :: OSI Approved :: Apache Software License
Classifier: Natural Language :: English
Classifier: Programming Language :: Python :: 2
Classifier: Programming Language :: Python :: 2.7
Classifier: Programming Language :: Python :: 3
Classifier: Programming Language :: Python :: 3.2
Classifier: Programming Language :: Python :: 3.3
Classifier: Programming Language :: Python :: 3.4
Classifier: Programming Language :: Python :: 3.5
Requires-Dist: jsonfield
Requires-Dist: python-dateutil
Requires-Dist: pytz
